MANIFEST.in
README.md
setup.py
edh_python_utilities/__init__.py
edh_python_utilities/cleanse.py
edh_python_utilities.egg-info/PKG-INFO
edh_python_utilities.egg-info/SOURCES.txt
edh_python_utilities.egg-info/dependency_links.txt
edh_python_utilities.egg-info/requires.txt
edh_python_utilities.egg-info/top_level.txt
edh_python_utilities/test_scripts/__init__.py
edh_python_utilities/test_scripts/test_date_cleanse.py
edh_python_utilities/test_scripts/test_experian_date_cleanse.py
edh_python_utilities/test_scripts/test_number_cleanse.py
edh_python_utilities/test_scripts/test_string_cleanse.py