Metadata-Version: 1.1
Name: edh-python-utilities
Version: 0.0.18
Summary: Python utilities for Influence Health's Enterprise Data Hub
Home-page: https://github.com/medseek-engineering/edh_python_utilities/tree/0.0.18
Author: Eric Meisel
Author-email: eric.meisel@influencehealth.com
License: UNKNOWN
Keywords: influence health influencehealth python utilities utility
Platform: UNKNOWN
Classifier: Programming Language :: Python :: 2.7
Classifier: Topic :: Text Processing
Classifier: Development Status :: 1 - Planning
